infinity_emb/__init__.py
infinity_emb/_optional_imports.py
infinity_emb/args.py
infinity_emb/cli.py
infinity_emb/engine.py
infinity_emb/env.py
infinity_emb/fastapi_schemas/__init__.py
infinity_emb/fastapi_schemas/data_uri.py
infinity_emb/fastapi_schemas/docs.py
infinity_emb/fastapi_schemas/errors.py
infinity_emb/fastapi_schemas/pydantic_v2.py
infinity_emb/fastapi_schemas/pymodels.py
infinity_emb/inference/__init__.py
infinity_emb/inference/batch_handler.py
infinity_emb/inference/caching_layer.py
infinity_emb/inference/loading_strategy.py
infinity_emb/inference/queue.py
infinity_emb/inference/select_model.py
infinity_emb/inference/threading_asyncio.py
infinity_emb/infinity_server.py
infinity_emb/log_handler.py
infinity_emb/primitives.py
infinity_emb/py.typed
infinity_emb/sync_engine.py
infinity_emb/telemetry.py
infinity_emb/transformer/__init__.py
infinity_emb/transformer/abstract.py
infinity_emb/transformer/acceleration.py
infinity_emb/transformer/audio/__init__.py
infinity_emb/transformer/audio/torch.py
infinity_emb/transformer/audio/utils.py
infinity_emb/transformer/classifier/__init__.py
infinity_emb/transformer/classifier/optimum.py
infinity_emb/transformer/classifier/torch.py
infinity_emb/transformer/crossencoder/__init__.py
infinity_emb/transformer/crossencoder/optimum.py
infinity_emb/transformer/crossencoder/torch.py
infinity_emb/transformer/embedder/__init__.py
infinity_emb/transformer/embedder/ct2.py
infinity_emb/transformer/embedder/dummytransformer.py
infinity_emb/transformer/embedder/neuron.py
infinity_emb/transformer/embedder/optimum.py
infinity_emb/transformer/embedder/sentence_transformer.py
infinity_emb/transformer/quantization/__init__.py
infinity_emb/transformer/quantization/interface.py
infinity_emb/transformer/quantization/quant.py
infinity_emb/transformer/utils.py
infinity_emb/transformer/utils_optimum.py
infinity_emb/transformer/vision/__init__.py
infinity_emb/transformer/vision/torch_vision.py
infinity_emb/transformer/vision/utils.py
infinity_emb-0.0.77.dist-info/METADATA
infinity_emb-0.0.77.dist-info/WHEEL
infinity_emb-0.0.77.dist-info/entry_points.txt
infinity_emb-0.0.77.dist-info/RECORD
