Metadata-Version: 2.1
Name: infinity_emb
Version: 0.0.77
Summary: Infinity is a high-throughput, low-latency REST API for serving text-embeddings, reranking models and clip.
Home-page: https://github.com/michaelfeil/infinity
License: MIT
Keywords: vector,embedding,neural,search,sentence-transformers
Author: michaelfeil
Author-email: noreply@michaelfeil.eu
Requires-Python: >=3.9,<3.14
Classifier: License :: OSI Approved :: MIT License
Classifier: Programming Language :: Python :: 3
Classifier: Programming Language :: Python :: 3.9
Classifier: Programming Language :: Python :: 3.10
Classifier: Programming Language :: Python :: 3.11
Classifier: Programming Language :: Python :: 3.12
Classifier: Programming Language :: Python :: 3.13
Provides-Extra: all
Provides-Extra: audio
Provides-Extra: cache
Provides-Extra: ct2
Provides-Extra: einops
Provides-Extra: logging
Provides-Extra: onnxruntime-gpu
Provides-Extra: optimum
Provides-Extra: server
Provides-Extra: tensorrt
Provides-Extra: torch
Provides-Extra: vision
Requires-Dist: colpali-engine (>=0.3.8,<0.4.0) ; extra == "vision" or extra == "all"
Requires-Dist: ctranslate2 (>=4.0.0) ; extra == "ct2" or extra == "all"
Requires-Dist: diskcache ; extra == "cache" or extra == "all"
Requires-Dist: einops ; extra == "einops" or extra == "all"
Requires-Dist: fastapi (>=0.103.2) ; extra == "server" or extra == "all"
Requires-Dist: huggingface_hub (>=0.32.0)
Requires-Dist: numpy (>=1.20.0,<2)
Requires-Dist: onnxruntime-gpu (==1.19.*) ; extra == "onnxruntime-gpu"
Requires-Dist: optimum[onnxruntime] (>=1.24.0) ; extra == "optimum" or extra == "all"
Requires-Dist: orjson (>=3.9.8,!=3.10.0) ; extra == "server" or extra == "all"
Requires-Dist: pillow ; extra == "vision" or extra == "all"
Requires-Dist: posthog ; extra == "server" or extra == "all"
Requires-Dist: prometheus-fastapi-instrumentator (>=6.1.0) ; extra == "server" or extra == "all"
Requires-Dist: pydantic (>=2.4.0,<3) ; extra == "server" or extra == "all"
Requires-Dist: rich (>=13,<14) ; extra == "logging" or extra == "server" or extra == "all"
Requires-Dist: sentence-transformers (>=3.0.1,<4.0.0) ; extra == "ct2" or extra == "torch" or extra == "all"
Requires-Dist: soundfile (>=0.12.1,<0.13.0) ; extra == "audio" or extra == "all"
Requires-Dist: tensorrt (>=10.6.0,<11.0.0) ; extra == "tensorrt"
Requires-Dist: timm ; extra == "vision" or extra == "all"
Requires-Dist: torch (>=2.2.1) ; extra == "ct2" or extra == "torch" or extra == "all"
Requires-Dist: torchvision ; extra == "vision" or extra == "all"
Requires-Dist: transformers[sentencepiece] (>=4.47.0,<=5.0) ; extra == "ct2"
Requires-Dist: typer (>=0.12.5,<0.13.0) ; extra == "server" or extra == "all"
Requires-Dist: uvicorn[standard] (>=0.32.0,<0.33.0) ; extra == "server" or extra == "all"
Project-URL: Repository, https://github.com/michaelfeil/infinity
